cleandat/__init__.py
cleandat/changelog.py
cleandat/cleanup.py
cleandat/constants.py
cleandat/date.py
cleandat/encoding.py
cleandat/pipeline.py
cleandat/workflows.py
tests/__init__.py
tests/test_cleanup.py
tests/test_date.py
tests/test_encoding.py
tests/test_pipeline.py
tests/test_workflows.py
cleandat-0.0.3.dist-info/LICENSE
cleandat-0.0.3.dist-info/METADATA
cleandat-0.0.3.dist-info/WHEEL
cleandat-0.0.3.dist-info/top_level.txt
cleandat-0.0.3.dist-info/RECORD
