Metadata-Version: 2.1
Name: cleandat
Version: 0.0.3
Summary: Python functions to facilitate the pre-processing of data for ML tasks in a clinical context.
Home-page: https://github.com/tiadams/cleandat
Author: Tim Adams
Author-email: tim-adams@gmx.net
License: MIT License
License-File: LICENSE
